run.py
setup.cfg
setup.py
http_here.egg-info/PKG-INFO
http_here.egg-info/SOURCES.txt
http_here.egg-info/dependency_links.txt
http_here.egg-info/entry_points.txt
http_here.egg-info/requires.txt
http_here.egg-info/top_level.txt