Metadata-Version: 1.1
Name: http-here
Version: 0.0.1
Summary: Simple Python HTTP server short for SimpleHTTPServer.
Home-page: https://github.com/hustcc
Author: hustcc
Author-email: i@hust.cc
License: MIT
Keywords: server,http,httpserver,simple,SimpleHTTPServer
Platform: UNKNOWN
Classifier: Intended Audience :: Developers
Classifier: Operating System :: OS Independent
Classifier: Natural Language :: Chinese (Simplified)
Classifier: Programming Language :: Python
Classifier: Programming Language :: Python :: 2
Classifier: Programming Language :: Python :: 2.5
Classifier: Programming Language :: Python :: 2.6
Classifier: Programming Language :: Python :: 2.7
Classifier: Programming Language :: Python :: 3
Classifier: Programming Language :: Python :: 3.2
Classifier: Programming Language :: Python :: 3.3
Classifier: Programming Language :: Python :: 3.4
Classifier: Programming Language :: Python :: 3.5
Classifier: Topic :: Utilities
